getnaive/__init__.py
getnaive/__main__.py
getnaive/app.py
getnaive/utils.py
getnaive-0.0.2.dist-info/LICENSE
getnaive-0.0.2.dist-info/METADATA
getnaive-0.0.2.dist-info/WHEEL
getnaive-0.0.2.dist-info/top_level.txt
getnaive-0.0.2.dist-info/RECORD
