Metadata-Version: 2.2
Name: getnaive
Version: 0.0.2
Summary: Analyze Native Resolution with Vapoursynth and more
Author: GabriellaChaos
Author-email: kageru <kageru@encode.moe>, Infi <infiziert@protonmail.ch>
Project-URL: Homepage, https://github.com/Gabriella-Chaos/vs-getnative
Classifier: Programming Language :: Python :: 3
Classifier: License :: OSI Approved :: MIT License
Classifier: Operating System :: OS Independent
Requires-Python: >=3.8
License-File: LICENSE
Requires-Dist: vapoursynth
Requires-Dist: numpy
Requires-Dist: scipy
